strands_mcp/__init__.py
strands_mcp/cli.py
strands_mcp/main.py
strands_mcp/server.py
strands_mcp/data/cache/chunk_1.md
strands_mcp/data/cache/chunk_10.md
strands_mcp/data/cache/chunk_11.md
strands_mcp/data/cache/chunk_12.md
strands_mcp/data/cache/chunk_13.md
strands_mcp/data/cache/chunk_14.md
strands_mcp/data/cache/chunk_15.md
strands_mcp/data/cache/chunk_16.md
strands_mcp/data/cache/chunk_17.md
strands_mcp/data/cache/chunk_18.md
strands_mcp/data/cache/chunk_19.md
strands_mcp/data/cache/chunk_2.md
strands_mcp/data/cache/chunk_20.md
strands_mcp/data/cache/chunk_21.md
strands_mcp/data/cache/chunk_22.md
strands_mcp/data/cache/chunk_23.md
strands_mcp/data/cache/chunk_24.md
strands_mcp/data/cache/chunk_25.md
strands_mcp/data/cache/chunk_26.md
strands_mcp/data/cache/chunk_27.md
strands_mcp/data/cache/chunk_28.md
strands_mcp/data/cache/chunk_29.md
strands_mcp/data/cache/chunk_3.md
strands_mcp/data/cache/chunk_30.md
strands_mcp/data/cache/chunk_31.md
strands_mcp/data/cache/chunk_32.md
strands_mcp/data/cache/chunk_33.md
strands_mcp/data/cache/chunk_34.md
strands_mcp/data/cache/chunk_35.md
strands_mcp/data/cache/chunk_36.md
strands_mcp/data/cache/chunk_37.md
strands_mcp/data/cache/chunk_38.md
strands_mcp/data/cache/chunk_39.md
strands_mcp/data/cache/chunk_4.md
strands_mcp/data/cache/chunk_40.md
strands_mcp/data/cache/chunk_41.md
strands_mcp/data/cache/chunk_42.md
strands_mcp/data/cache/chunk_43.md
strands_mcp/data/cache/chunk_44.md
strands_mcp/data/cache/chunk_45.md
strands_mcp/data/cache/chunk_46.md
strands_mcp/data/cache/chunk_47.md
strands_mcp/data/cache/chunk_48.md
strands_mcp/data/cache/chunk_49.md
strands_mcp/data/cache/chunk_5.md
strands_mcp/data/cache/chunk_50.md
strands_mcp/data/cache/chunk_51.md
strands_mcp/data/cache/chunk_52.md
strands_mcp/data/cache/chunk_53.md
strands_mcp/data/cache/chunk_54.md
strands_mcp/data/cache/chunk_55.md
strands_mcp/data/cache/chunk_56.md
strands_mcp/data/cache/chunk_57.md
strands_mcp/data/cache/chunk_58.md
patersr_strands_mcp_server-0.2.5.dist-info/METADATA
patersr_strands_mcp_server-0.2.5.dist-info/WHEEL
patersr_strands_mcp_server-0.2.5.dist-info/entry_points.txt
patersr_strands_mcp_server-0.2.5.dist-info/licenses/LICENSE
patersr_strands_mcp_server-0.2.5.dist-info/RECORD
