Metadata-Version: 2.4
Name: patersr-strands-mcp-server
Version: 0.2.5
Summary: MCP server for Strands Agent SDK documentation search and project assistance
Project-URL: Homepage, https://github.com/robpaterson/strands-mcp-server
Project-URL: Repository, https://github.com/robpaterson/strands-mcp-server
Project-URL: Issues, https://github.com/robpaterson/strands-mcp-server/issues
Author-email: Rob Paterson <your-email@example.com>
License: MIT
License-File: LICENSE
Keywords: agents,documentation,llm,mcp,strands
Classifier: Development Status :: 3 - Alpha
Classifier: Intended Audience :: Developers
Classifier: License :: OSI Approved :: MIT License
Classifier: Programming Language :: Python :: 3
Classifier: Programming Language :: Python :: 3.11
Classifier: Programming Language :: Python :: 3.12
Requires-Python: >=3.11
Requires-Dist: aiofiles>=23.2.0
Requires-Dist: boto3>=1.34.0
Requires-Dist: click>=8.1.0
Requires-Dist: faiss-cpu>=1.12.0
Requires-Dist: fastmcp>=0.1.0
Requires-Dist: httpx>=0.27.0
Requires-Dist: mcp>=1.0.0
Requires-Dist: numpy<2.0.0
Requires-Dist: platformdirs<4.0.0,>=3.0.0
Requires-Dist: pydantic>=2.5.0
Provides-Extra: dev
Requires-Dist: black>=23.12.0; extra == 'dev'
Requires-Dist: mypy>=1.8.0; extra == 'dev'
Requires-Dist: pytest-asyncio>=0.21.0; extra == 'dev'
Requires-Dist: pytest>=7.4.0; extra == 'dev'
Requires-Dist: ruff>=0.1.8; extra == 'dev'
